syscopt/__init__.py
syscopt/cli_handlers.py
syscopt/syscopt-cli
syscopt/APIs/__init__.py
syscopt/APIs/apy.py
syscopt/settings/__init__.py
syscopt/settings/settings.dis.json
syscopt/solver/DIS.py
syscopt/solver/__init__.py
syscopt/solver/common.py
syscopt/solver/exeptions.py
syscopt/solver/syscopt.py
syscopt/solver/algs/__init__.py
syscopt/solver/algs/distributedprimalsolver.py
syscopt/solver/algs/solver.py
syscopt/solver/model/__init__.py
syscopt/solver/model/domain.py
syscopt/solver/model/parsers.py
syscopt/solver/model/validators.py
syscopt-0.1.5.dist-info/METADATA
syscopt-0.1.5.dist-info/WHEEL
syscopt-0.1.5.dist-info/top_level.txt
syscopt-0.1.5.dist-info/RECORD
